statkit/__init__.py
statkit/dataset.py
statkit/decision.py
statkit/feature_selection.py
statkit/metrics.py
statkit/non_parametric.py
statkit/power.py
statkit/types.py
statkit/views.py
statkit-1.0.3.dist-info/METADATA
statkit-1.0.3.dist-info/WHEEL
statkit-1.0.3.dist-info/licenses/LICENSE
statkit-1.0.3.dist-info/RECORD
