Metadata-Version: 2.4
Name: statkit
Version: 1.0.3
Summary: Confidence intervals and p-values for sci-kit learn.
Project-URL: Homepage, https://gitlab.com/hylkedonker/statkit
Project-URL: Bug Tracker, https://gitlab.com/hylkedonker/statkit/-/issues
Author-email: "H. C. Donker" <h.c.donker@umcg.nl>
License: MIT License
License-File: LICENSE
Classifier: License :: OSI Approved :: MIT License
Classifier: Operating System :: OS Independent
Classifier: Programming Language :: Python :: 3
Requires-Python: >=3.10
Requires-Dist: numpy
Requires-Dist: pandas
Requires-Dist: scikit-learn
Requires-Dist: scipy
Requires-Dist: statsmodels
